{
    "version": "0.5.11",
    "architecture": {
        "64bit": {
            "url": "https://github.com/kaufmann-dev/git-wrangler/releases/download/v0.5.11/git-wrangler_0.5.11_windows_amd64.zip",
            "bin": [
                "git-wrangler.exe"
            ],
            "hash": "5e7b538921ef85544045bfcc1c115cf8b7ee1c93675d7e4d2f4a35735a5d6ae9"
        },
        "arm64": {
            "url": "https://github.com/kaufmann-dev/git-wrangler/releases/download/v0.5.11/git-wrangler_0.5.11_windows_arm64.zip",
            "bin": [
                "git-wrangler.exe"
            ],
            "hash": "5580f7bea48eb78163fadf2871d11d5800803a17b663357d6cea20cf76eb488b"
        }
    },
    "homepage": "https://github.com/kaufmann-dev/git-wrangler",
    "license": "MIT",
    "description": "Orchestrate Git operations across many repositories.",
    "depends": [
        "git",
        "gh",
        "git-filter-repo"
    ]
}
