{
    "version": "0.5.12",
    "architecture": {
        "64bit": {
            "url": "https://github.com/kaufmann-dev/git-wrangler/releases/download/v0.5.12/git-wrangler_0.5.12_windows_amd64.zip",
            "bin": [
                "git-wrangler.exe"
            ],
            "hash": "67fd20a70562d4e1e4c11f647509ab6ced42a87217d82858a6b0546a67f42774"
        },
        "arm64": {
            "url": "https://github.com/kaufmann-dev/git-wrangler/releases/download/v0.5.12/git-wrangler_0.5.12_windows_arm64.zip",
            "bin": [
                "git-wrangler.exe"
            ],
            "hash": "8b70de6f8421bc48ea23ca142241013ef8c4331e6f898700c8bdfd075d816c6b"
        }
    },
    "homepage": "https://github.com/kaufmann-dev/git-wrangler",
    "license": "MIT",
    "description": "Orchestrate Git operations across many repositories.",
    "depends": [
        "git",
        "gh",
        "git-filter-repo"
    ]
}
